{"stat.drop.minecraft.gunpowder":4,"stat.useItem.thermalfoundation.tool.pickaxe_lead":100,"stat.useItem.actuallyadditions.item_rice_seed":8,"stat.pickup.minecraft.rotten_flesh":119,"stat.useItem.minecraft.diamond_hoe":19,"stat.useItem.chisel.marble":1,"stat.killEntity.twilightforest.raven":2,"stat.pickup.minecraft.bucket":2,"stat.useItem.traverse.fir_door":1,"stat.pickup.instrumentalmobs.drum_block":2,"stat.killEntity.Enderman":1,"stat.craftItem.botania.storage":1,"stat.pickup.quark.tallow":12,"stat.pickup.astralsorcery.blocklens":16,"stat.mineBlock.chisel.marble2":223,"stat.mineBlock.chisel.marble1":1,"stat.useItem.actuallyadditions.item_coffee_seed":11,"stat.furnaceInteraction":266,"stat.pickup.elevatorid.elevator_lime":1,"stat.pickup.minecraft.nether_brick":50,"stat.entityKilledBy.WitherSkeleton":1,"stat.drop.twilightforest.twilight_plant":1,"stat.mineBlock.botania.terraplate":8,"stat.useItem.quark.marble":564,"stat.useItem.minecraft.fence":31,"stat.pickup.actuallyadditions.item_crystal":1,"stat.drop.thermalfoundation.tome_experience":2,"stat.pickup.botania.rune":9,"stat.craftItem.botania.pool":3,"stat.useItem.minecraft.flint_and_steel":12,"stat.mineBlock.minecraft.fence":1,"stat.useItem.minecraft.wheat_seeds":31,"stat.mineBlock.astralsorcery.blockmarble":778,"stat.killEntity.twilightforest.naga":1,"stat.useItem.botania.twigwand":424,"stat.pickup.minecraft.emerald":9,"stat.useItem.twilightforest.knightmetal_axe":98,"stat.deaths":19,"stat.pickup.minecraft.bowl":1,"stat.pickup.minecraft.egg":10,"stat.useItem.actuallyadditions.item_sword_crystal_green":205,"stat.pickup.tconstruct.moms_spaghetti":4,"stat.chestOpened":1230,"stat.craftItem.traverse.fir_planks":44,"stat.useItem.draconicevolution.infused_obsidian":7,"stat.pickup.botania.mushroom":1,"stat.useItem.botania.managlass":601,"stat.mineBlock.actuallyadditions.block_tiny_torch":12,"stat.killEntity.twilightforest.yeti":9,"stat.pickup.minecraft.gold_nugget":14,"stat.craftItem.minecraft.coal":254,"stat.mineBlock.botania.mushroom":1,"stat.mineBlock.astralsorcery.blockmarbleslab":27,"stat.craftItem.twilightforest.block_storage":2,"stat.pickup.botania.lexicon":1,"stat.pickup.minecraft.carrot":38,"stat.crouchOneCm":191317,"stat.craftItem.minecraft.iron_ingot":146,"stat.craftingTableInteraction":168,"stat.drop.thermalfoundation.ore":1,"stat.mineBlock.minecraft.wooden_pressure_plate":5,"stat.craftItem.thermalexpansion.satchel":1,"stat.craftItem.simplybackpacks.commonbackpack":1,"stat.drop.actuallyadditions.block_tiny_torch":1,"stat.pickup.minecraft.dye":12,"stat.pickup.minecraft.planks":886,"stat.pickup.chisel.limestone2":92,"stat.mineBlock.xlfoodmod.grass":12,"stat.pickup.minecraft.ice":10871,"stat.mineBlock.actuallyadditions.block_black_lotus":4,"stat.drop.minecraft.rotten_flesh":19,"stat.mineBlock.draconicevolution.draconium_ore":51,"stat.killEntity.twilightforest.slime_beetle":3,"stat.pickup.twilightforest.underbrick":1,"stat.pickup.botania.flowerbag":5,"stat.useItem.actuallyadditions.item_canola_seed":4,"stat.useItem.actuallyadditions.item_sword_quartz":53,"stat.pickup.astralsorcery.blockwell":1,"stat.drop.minecraft.iron_ore":2,"stat.craftItem.draconicevolution.draconium_ingot":119,"stat.mineBlock.twilightforest.twilight_leaves":10,"stat.pickup.quark.soul_bead":14,"stat.pickup.twilightforest.block_storage":2,"stat.mineBlock.actuallyadditions.block_atomic_reconstructor":1,"stat.craftItem.minecraft.bucket":3,"stat.craftItem.minecraft.planks":1100,"stat.pickup.minecraft.stone_sword":11,"stat.craftItem.minecraft.fishing_rod":1,"stat.pickup.minecraft.book":4,"stat.useItem.minecraft.stonebrick":1,"stat.pickup.botania.cacophonium":2,"stat.drop.botania.twigwand":1,"stat.killEntity.twilightforest.blockchain_goblin":1,"stat.pickup.quark.pickarang":1,"stat.mineBlock.astralsorcery.blockworldilluminator":1,"stat.drop.chisel.chisel_diamond":1,"stat.drop.astralsorcery.blockmarble":13,"stat.mineBlock.minecraft.cobblestone":86,"stat.pickup.minecraft.flint":6,"stat.craftItem.botania.alfheimportal":1,"stat.pickup.botania.alchemycatalyst":1,"stat.mineBlock.quark.stone_marble_slab":17,"stat.pickup.astralsorcery.itemcoloredlens":1,"stat.mineBlock.botania.runealtar":2,"stat.mineBlock.chisel.marble":4,"stat.useItem.minecraft.stone_slab2":441,"stat.drop.twilightforest.lamp_of_cinders":2,"stat.pickup.astralsorcery.blockattunementrelay":2,"stat.pickup.forge.bucketfilled":3,"stat.pickup.minecraft.iron_boots":1,"stat.pickup.actuallyadditions.block_giant_chest":6,"stat.killEntity.instrumentalmobs:DrumZombie":19,"stat.craftItem.minecraft.furnace":3,"stat.craftItem.minecraft.lapis_block":10,"stat.pickup.thermalfoundation.ore":23,"stat.pickup.actuallyadditions.block_quartz_stair":6,"stat.craftItem.twilightforest.fiery_leggings":2,"stat.pickup.quark.black_ash":108,"stat.mineBlock.minecraft.clay":1,"stat.mineBlock.elevatorid.elevator_lime":1,"stat.pickup.chisel.netherrack":109,"stat.pickup.twilightforest.twilight_sapling":4,"stat.drop.minecraft.spider_eye":1,"stat.craftItem.minecraft.iron_block":11,"stat.craftItem.thermalfoundation.tool.pickaxe_lead":1,"stat.pickup.actuallyadditions.block_crystal":1,"stat.pickup.twilightforest.naga_scale":13,"stat.pickup.xlfoodmod.cucumber_seeds":1,"stat.drop.minecraft.flint_and_steel":1,"stat.killEntity.Creeper":24,"stat.pickup.minecraft.wooden_sword":3,"stat.entityKilledBy.Skeleton":2,"stat.pickup.twilightforest.carminite":3,"stat.killEntity.twilightforest.pinch_beetle":5,"stat.killEntity.Squid":1,"stat.sprintOneCm":3845653,"stat.mineBlock.minecraft.stone_slab":2,"stat.pickup.twilightforest.steeleaf_ingot":9,"stat.killEntity.Zombie":71,"stat.craftItem.minecraft.dye":126,"stat.mineBlock.minecraft.gold_ore":5,"stat.drop.minecraft.diamond_pickaxe":2,"stat.pickup.minecraft.wheat":69,"stat.mineBlock.minecraft.mossy_cobblestone":3,"stat.pickup.instrumentalmobs.maraca":2,"stat.mineBlock.astralsorcery.blockmarblestairs":32,"stat.pickup.minecraft.sign":2,"stat.craftItem.minecraft.cooked_porkchop":35,"stat.craftItem.botania.altar":1,"stat.pickup.minecraft.obsidian":24,"stat.mineBlock.botania.spreader":10,"stat.pickup.xlfoodmod.onion":1,"stat.pickup.minecraft.coal":193,"stat.pickup.minecraft.iron_ingot":42,"stat.pickup.thermalfoundation.tome_experience":3,"stat.pickup.actuallyadditions.block_black_lotus":7,"stat.drop.minecraft.diamond_sword":2,"stat.pickup.minecraft.gunpowder":40,"stat.pickup.minecraft.dirt":686,"stat.useItem.astralsorcery.blockblackmarble":46,"stat.killEntity.quark:wraith":5,"stat.craftItem.twilightforest.fiery_chestplate":2,"stat.mineBlock.minecraft.torch":55,"stat.pickup.minecraft.written_book":1,"stat.mineBlock.minecraft.red_flower":60,"stat.craftItem.thermalfoundation.tool.shield_iron":2,"stat.pickup.astralsorcery.blockcustomore":4,"stat.pickup.botania.spreader":11,"stat.drop.actuallyadditions.item_food":1,"stat.mineBlock.chisel.netherrack":108,"stat.useItem.thermalfoundation.tool.hammer_diamond":1482,"stat.drop.minecraft.wheat":1,"stat.pickup.minecraft.diamond_pickaxe":4,"stat.useItem.minecraft.lava_bucket":1,"stat.useItem.minecraft.gold_ore":1,"stat.useItem.actuallyadditions.item_worm":2,"stat.drop.minecraft.netherrack":3,"stat.drop.botania.blacklotus":30,"stat.mineBlock.twilightforest.trollvidr":3,"stat.pickup.astralsorcery.itemcrystalpickaxe":4,"stat.craftItem.botania.turntable":1,"stat.pickup.minecraft.cooked_beef":17,"stat.pickup.actuallyadditions.item_coffee_beans":39,"stat.mineBlock.chisel.netherbrick":2,"stat.pickup.twilightforest.arctic_helmet":1,"stat.mobKills":590,"stat.drop.minecraft.written_book":1,"stat.useItem.quark.pickarang":70,"stat.pickup.minecraft.diamond":60,"stat.pickup.astralsorcery.blockmarble":1345,"stat.pickup.botania.livingrock":48,"stat.craftItem.draconicevolution.energy_infuser":1,"stat.killEntity.Blaze":157,"stat.pickup.minecraft.golden_boots":1,"stat.pickup.minecraft.glowstone_dust":68,"stat.drop.minecraft.bowl":3,"stat.pickup.twilightforest.zombie_scepter":1,"stat.useItem.twilightforest.meef_stroganoff":1,"stat.mineBlock.minecraft.red_mushroom":3,"stat.mineBlock.minecraft.nether_brick_fence":26,"stat.pickup.twilightforest.lifedrain_scepter":2,"stat.pickup.twilightforest.hydra_chop":15,"stat.mineBlock.twilightforest.twilight_log":7,"stat.craftItem.minecraft.stone_sword":2,"stat.mineBlock.minecraft.sand":551,"stat.killEntity.twilightforest.kobold":2,"stat.drop.astralsorcery.itemcrystalsword":7,"stat.hopperInspected":8,"stat.drop.minecraft.diamond":10,"stat.pickup.minecraft.ghast_tear":3,"stat.craftItem.thermalfoundation.armor.plate_silver":1,"stat.mineBlock.botania.managlass":6,"stat.pickup.minecraft.wooden_button":1,"stat.craftItem.thermalfoundation.material":78,"stat.mineBlock.minecraft.lapis_block":16,"stat.pickup.actuallyadditions.item_sword_quartz":1,"stat.useItem.astralsorcery.itemcrystalsword":992,"stat.killEntity.Horse":1,"stat.pickup.minecraft.stone_stairs":44,"stat.pickup.instrumentalmobs.french_horn":1,"stat.mineBlock.minecraft.soul_sand":15,"stat.pickup.minecraft.blaze_rod":138,"stat.useItem.chisel.netherbrick":7,"stat.craftItem.minecraft.diamond_block":1,"stat.mineBlock.actuallyadditions.block_wild":4,"stat.pickup.minecraft.netherrack":1240,"stat.mineBlock.botania.specialflower":15,"stat.mineBlock.minecraft.ice":4646,"stat.pickup.chisel.marblepillar":29,"stat.craftItem.minecraft.iron_hoe":1,"stat.drop.xlfoodmod.salt":4,"stat.useItem.minecraft.experience_bottle":50,"stat.pickup.twilightforest.knightmetal_pickaxe":1,"stat.pickup.minecraft.golden_leggings":3,"stat.pickup.thermalfoundation.tool.pickaxe_nickel":1,"stat.craftItem.quark.marble":297,"stat.pickup.astralsorcery.itemcrystalaxe":1,"stat.drop.minecraft.bone":4,"stat.craftItem.minecraft.wooden_button":2,"stat.useItem.minecraft.furnace":4,"stat.pickup.minecraft.iron_leggings":10,"stat.mineBlock.botania.pool":4,"stat.mineBlock.minecraft.gravel":36,"stat.drop.twilightforest.giant_sword":2,"stat.pickup.twilightforest.knightmetal_sword":1,"stat.craftItem.twilightforest.naga_leggings":1,"stat.craftItem.simplybackpacks.uncommonbackpack":1,"stat.pickup.minecraft.flint_and_steel":1,"stat.useItem.minecraft.torch":78,"stat.craftItem.minecraft.redstone_block":68,"stat.pickup.minecraft.crafting_table":12,"stat.useItem.minecraft.log":10,"stat.craftItem.minecraft.crafting_table":6,"stat.pickup.thermalfoundation.tool.hammer_diamond":6,"stat.drop.minecraft.sign":1,"stat.pickup.twilightforest.shield_scepter":1,"stat.pickup.astralsorcery.blockaltar":6,"stat.useItem.quark.world_stone_bricks":30,"stat.pickup.minecraft.web":10,"stat.mineBlock.actuallyadditions.block_giant_chest_medium":1,"stat.pickup.minecraft.sapling":7,"stat.drop.minecraft.bow":2,"stat.mineBlock.quark.basalt":3,"stat.mineBlock.actuallyadditions.block_laser_relay":2,"stat.pickup.refinedstorage.wireless_transmitter":1,"stat.killEntity.WitherSkeleton":40,"stat.pickup.minecraft.golden_sword":1,"stat.craftItem.botania.twigwand":1,"stat.useItem.minecraft.baked_potato":152,"stat.pickup.minecraft.stone_slab":10,"stat.drop.minecraft.yellow_flower":4,"stat.pickup.minecraft.yellow_flower":31,"stat.drop.minecraft.ghast_tear":2,"stat.killEntity.twilightforest.lich":1,"stat.craftItem.minecraft.diamond_chestplate":1,"stat.pickup.minecraft.bone":251,"stat.useItem.minecraft.mushroom_stew":1,"stat.craftItem.minecraft.sticky_piston":1,"stat.pickup.minecraft.redstone_torch":4,"stat.useItem.astralsorcery.blockmarblestairs":121,"stat.craftItem.botania.magnetring":1,"stat.useItem.minecraft.diamond_sword":351,"stat.craftItem.tconstruct.slimesling":2,"stat.pickup.twilightforest.giant_obsidian":1,"stat.climbOneCm":7833,"stat.pickup.refinedstorage.external_storage":2,"stat.craftItem.minecraft.gold_block":8,"stat.pickup.chisel.marble":3,"stat.drop.minecraft.quartz":6,"stat.useItem.minecraft.red_flower":6,"stat.useItem.twilightforest.giant_sword":4,"stat.pickup.twilightforest.steeleaf_chestplate":2,"stat.drop.minecraft.web":3,"stat.craftItem.minecraft.stone_pickaxe":3,"stat.pickup.minecraft.cobblestone":3743,"stat.craftItem.botania.alchemycatalyst":1,"stat.craftItem.minecraft.glass_bottle":3,"stat.pickup.minecraft.soul_sand":8,"stat.mineBlock.quark.custom_chest":2,"stat.useItem.astralsorcery.blockmarbleslab":335,"stat.useItem.minecraft.cooked_beef":25,"stat.drop.twilightforest.trophy":2,"stat.pickup.minecraft.redstone":33,"stat.mineBlock.minecraft.iron_ore":27,"stat.craftItem.minecraft.book":2,"stat.mineBlock.xlfoodmod.vanilla_flower":2,"stat.pickup.minecraft.mossy_cobblestone":3,"stat.pickup.actuallyadditions.item_rice_seed":16,"stat.craftItem.astralsorcery.blockmarbleslab":366,"stat.mineBlock.thermalfoundation.ore":16,"stat.useItem.twilightforest.knightmetal_pickaxe":1,"stat.drop.instrumentalmobs.french_horn":1,"stat.drop.minecraft.dirt":22,"stat.useItem.minecraft.cooked_porkchop":40,"stat.pickup.minecraft.diamond_shovel":1,"stat.mineBlock.botania.turntable":1,"stat.craftItem.botania.travelbelt":1,"stat.craftItem.tconstruct.slime_boots":5,"stat.pickup.botania.petal":274,"stat.pickup.chisel.glass":618,"stat.pickup.actuallyadditions.block_tiny_torch":79,"stat.craftItem.botania.manaresource":13,"stat.pickup.minecraft.paper":34,"stat.useItem.botania.lexicon":1,"stat.craftItem.minecraft.stick":220,"stat.craftItem.minecraft.gold_nugget":9,"stat.pickup.minecraft.grass":99,"stat.drop.botania.auraring":1,"stat.pickup.botania.flower":6,"stat.mineBlock.minecraft.planks":11,"stat.drop":429,"stat.killEntity.twilightforest.knight_phantom":1,"stat.craftItem.actuallyadditions.item_misc":5,"stat.pickup.actuallyadditions.block_giant_chest_medium":1,"stat.killEntity.Sheep":8,"stat.mineBlock.astralsorcery.blockmachine":7,"stat.craftItem.minecraft.piston":2,"stat.useItem.actuallyadditions.block_tiny_torch":47,"stat.mineBlock.traverse.red_autumnal_leaves":2,"stat.drop.astralsorcery.blockmachine":1,"stat.mineBlock.botania.doubleflower2":2,"stat.mineBlock.botania.doubleflower1":2,"stat.useItem.chisel.marblepillar":20,"stat.drop.minecraft.cooked_beef":3,"stat.killEntity.Slime":10,"stat.pickup.twilightforest.giant_sword":2,"stat.useItem.minecraft.apple":1,"stat.pickup.twilightforest.torchberries":7,"stat.pickup.minecraft.fence":6,"stat.useItem.minecraft.stone_axe":87,"stat.pickup.twilightforest.twilight_plant":1,"stat.craftItem.minecraft.iron_helmet":1,"stat.pickup.actuallyadditions.block_misc":5,"stat.drop.minecraft.glass":628,"stat.pickup.astralsorcery.itemusabledust":68,"stat.craftItem.minecraft.flint_and_steel":1,"stat.pickup.actuallyadditions.item_coffee_seed":27,"stat.mineBlock.tconstruct.tooltables":2,"stat.pickup.xlfoodmod.tomato_seeds":2,"stat.mineBlock.minecraft.furnace":7,"stat.mineBlock.traverse.fir_door":2,"stat.useItem.twilightforest.canopy_planks":23,"stat.killEntity.CaveSpider":2,"stat.craftItem.minecraft.netherbrick":5,"stat.craftItem.botania.manatablet":1,"stat.pickup.minecraft.oak_stairs":2,"stat.craftItem.simplybackpacks.rarebackpack":2,"stat.damageDealt":114427,"stat.pickup.actuallyadditions.item_canola_seed":11,"stat.useItem.minecraft.crafting_table":3,"stat.pickup.twilightforest.castle_door":176,"stat.pickup.minecraft.stick":69,"stat.mineBlock.botania.altar":2,"stat.useItem.actuallyadditions.item_jam":18,"stat.pickup.minecraft.air":0,"stat.killEntity.Chicken":1,"stat.mineBlock.minecraft.quartz_ore":20,"stat.pickup.quark.world_stone_bricks":43,"stat.pickup.twilightforest.knightmetal_axe":2,"stat.craftItem.minecraft.fence":51,"stat.craftItem.thermalfoundation.armor.legs_silver":2,"stat.mineBlock.minecraft.leaves":36,"stat.drop.quark.stone_marble_slab":2,"stat.pickup.instrumentalmobs.drum":1,"stat.killEntity.twilightforest.wild_boar":1,"stat.craftItem.quark.stone_marble_slab":60,"stat.pickup.astralsorcery.itemwand":8,"stat.pickup.astralsorcery.blockcollectorcrystal":4,"stat.pickup.draconicevolution.draconium_dust":131,"stat.useItem.botania.flowerbag":6,"stat.leaveGame":41,"stat.useItem.twilightforest.hydra_chop":20,"stat.craftItem.thermalfoundation.armor.helmet_platinum":1,"stat.pickup.tconstruct.edible":22,"stat.craftItem.minecraft.ender_eye":5,"stat.killEntity.PigZombie":7,"stat.pickup.botania.manatablet":7,"stat.craftItem.minecraft.shield":2,"stat.craftItem.botania.lens":2,"stat.useItem.elevatorid.elevator_white":1,"stat.killEntity.twilightforest.armored_giant":1,"stat.pickup.quark.basalt":72,"stat.useItem.astralsorcery.itemcoloredlens":1,"stat.craftItem.botania.autocraftinghalo":1,"stat.killEntity.Witch":5,"stat.mineBlock.actuallyadditions.block_coal_generator":1,"stat.craftItem.traverse.fir_door":3,"stat.craftItem.enderstorage.ender_storage":4,"stat.craftItem.minecraft.bed":1,"stat.mineBlock.minecraft.vine":6,"stat.pickup.thermalfoundation.material":101,"stat.pickup.botania.thornchakram":3,"stat.mineBlock.botania.flower":104,"stat.killEntity.ZombieVillager":9,"stat.mineBlock.traverse.fir_log":7,"stat.killEntity.twilightforest.tower_ghast":2,"stat.drop.minecraft.red_flower":2,"stat.pickup.botania.livingwood":28,"stat.pickup.minecraft.beef":39,"stat.pickup.twilightforest.twilight_scepter":2,"stat.pickup.minecraft.potion":1,"stat.useItem.minecraft.wooden_button":1,"stat.pickup.xlfoodmod.salt":35,"stat.craftItem.botania.runealtar":1,"stat.entityKilledBy.twilightforest.minotaur":1,"stat.mineBlock.enderstorage.ender_storage":6,"stat.pickup.tconstruct.stone_torch":6,"stat.pickup.astralsorcery.blockmarblestairs":41,"stat.pickup.twilightforest.armor_shard":4,"stat.craftItem.thermalfoundation.armor.boots_silver":1,"stat.drop.minecraft.glass_bottle":2,"stat.drop.minecraft.torch":1,"stat.pickup.chisel.marble1":1,"stat.pickup.chisel.marble2":317,"stat.craftItem.botania.livingwood":3,"stat.mineBlock.minecraft.tallgrass":779,"stat.pickup.quark.stone_basalt_stairs":11,"stat.useItem.minecraft.stone":16,"stat.pickup.minecraft.arrow":109,"stat.pickup.minecraft.wooden_pressure_plate":5,"stat.killEntity.Ghast":4,"stat.mineBlock.twilightforest.trollber":1,"stat.pickup.astralsorcery.itemcrystalsword":9,"stat.mineBlock.elevatorid.elevator_white":3,"stat.mineBlock.minecraft.chest":31,"stat.pickup.actuallyadditions.item_food":12,"stat.pickup.minecraft.painting":6,"stat.craftItem.minecraft.hopper":1,"stat.pickup.minecraft.nether_brick_fence":38,"stat.useItem.astralsorcery.itemcrystalaxe":9,"stat.craftItem.thermalfoundation.armor.helmet_silver":1,"stat.useItem.chisel.marble2":21,"stat.craftItem.minecraft.wooden_sword":9,"stat.craftItem.draconicevolution.draconic_core":23,"stat.craftItem.draconicevolution.infused_obsidian":9,"stat.craftItem.minecraft.diamond_shovel":2,"stat.pickup.minecraft.wheat_seeds":155,"stat.pickup.chisel.cobblestone":4,"stat.pickup.twilightforest.maze_stone":10,"stat.drop.twilightforest.torchberries":2,"stat.mineBlock.minecraft.dirt":705,"stat.mineBlock.twilightforest.unripe_trollber":1,"stat.pickup.minecraft.poisonous_potato":5,"stat.useItem.minecraft.bread":14,"stat.drop.actuallyadditions.item_worm":5,"stat.useItem.minecraft.cobblestone":373,"stat.useItem.minecraft.gravel":3,"stat.mineBlock.minecraft.double_plant":4,"stat.useItem.twilightforest.giant_log":2,"stat.pickup.botania.blacklotus":12,"stat.drop.minecraft.carrot":1,"stat.craftItem.minecraft.gold_ingot":30,"stat.craftItem.minecraft.brewing_stand":2,"stat.pickup.thermalexpansion.florb":2,"stat.pickup.minecraft.apple":1,"stat.pickup.traverse.fir_planks":4,"stat.itemEnchanted":11,"stat.useItem.twilightforest.castle_door":13,"stat.mineBlock.minecraft.log":28,"stat.drop.chisel.netherrack":3,"stat.craftItem.botania.pylon":4,"stat.craftItem.minecraft.paper":6,"stat.pickup.minecraft.red_flower":69,"stat.pickup.minecraft.wool":36,"stat.pickup.twilightforest.aurora_block":64,"stat.mineBlock.chisel.marblepillar":14,"stat.drop.botania.manaresource":6,"stat.pickup.astralsorcery.blockblackmarble":507,"stat.craftItem.astralsorcery.blockmarblestairs":108,"stat.craftItem.twilightforest.canopy_planks":24,"stat.craftItem.storagedrawers.basicdrawers":1,"stat.drop.minecraft.stone_shovel":2,"stat.mineBlock.minecraft.yellow_flower":34,"stat.entityKilledBy.Witch":1,"stat.craftItem.twilightforest.fiery_ingot":7,"stat.drop.thermalfoundation.material":3,"stat.mineBlock.astralsorcery.blockcustomore":8,"stat.mineBlock.actuallyadditions.block_crystal":1,"stat.useItem.minecraft.obsidian":5,"stat.mineBlock.actuallyadditions.block_canola_press":1,"stat.pickup.minecraft.bow":6,"stat.mineBlock.chisel.cobblestone":4,"stat.useItem.minecraft.egg":4,"stat.craftItem.minecraft.cooked_beef":19,"stat.mineBlock.minecraft.obsidian":16,"stat.pickup.minecraft.shears":1,"stat.pickup.minecraft.iron_trapdoor":1,"stat.craftItem.elevatorid.elevator_red":1,"stat.pickup.minecraft.diamond_hoe":1,"stat.flyOneCm":8506331,"stat.pickup.actuallyadditions.item_booklet":1,"stat.killEntity.twilightforest.mini_ghast":32,"stat.timeSinceDeath":253405,"stat.pickup.astralsorcery.itemcrystalshovel":1,"stat.craftItem.draconicevolution.generator":1,"stat.mineBlock.botania.livingwood":8,"stat.pickup.minecraft.nether_wart":23,"stat.mineBlock.astralsorcery.blockblackmarble":49,"stat.drop.astralsorcery.itemrockcrystalsimple":4,"stat.mineBlock.minecraft.coal_ore":35,"stat.pickup.minecraft.shield":1,"stat.talkedToVillager":2,"stat.mineBlock.actuallyadditions.block_coffee_machine":1,"stat.pickup.botania.manaresource":116,"stat.pickup.minecraft.string":76,"stat.useItem.minecraft.milk_bucket":1,"stat.pickup.astralsorcery.blockmachine":10,"stat.useItem.minecraft.written_book":1,"stat.pickup.twilightforest.knightmetal_ingot":16,"stat.useItem.minecraft.diamond_shovel":830,"stat.pickup.refinedstorageaddons.wireless_crafting_grid":1,"stat.useItem.enderstorage.ender_storage":1,"stat.mineBlock.minecraft.diamond_ore":55,"stat.mineBlock.refinedstorage.external_storage":2,"stat.useItem.actuallyadditions.item_coffee_beans":4,"stat.mineBlock.quark.marble":2694,"stat.pickup.minecraft.spawn_egg":2,"stat.pickup.refinedstorage.upgrade":2,"stat.craftItem.thermalfoundation.armor.legs_platinum":1,"stat.mineBlock.xlfoodmod.rock_salt":6,"stat.diveOneCm":42892,"stat.pickup.tconstruct.tooltables":2,"stat.pickup.storagedrawers.basicdrawers":12,"stat.pickup.botania.grassseeds":1,"stat.mineBlock.traverse.fir_leaves":1,"stat.pickup.minecraft.stone_axe":3,"stat.jump":18069,"stat.useItem.actuallyadditions.item_flax_seed":3,"stat.craftItem.twilightforest.arctic_chestplate":1,"stat.useItem.minecraft.sand":7,"stat.useItem.astralsorcery.itemcrystalshovel":251,"stat.useItem.botania.tinypotato":1,"stat.craftItem.minecraft.torch":424,"stat.pickup.botania.runealtar":3,"stat.useItem.astralsorcery.itemcrystalpickaxe":1419,"stat.pickup.minecraft.stone_shovel":2,"stat.pickup.minecraft.gold_ore":5,"stat.pickup.draconicevolution.generator":1,"stat.pickup.actuallyadditions.item_flax_seed":6,"stat.damageTaken":24206,"stat.pickup.twilightforest.firefly":1,"stat.mineBlock.botania.tinypotato":2,"stat.killEntity.tconstruct.blueslime":9,"stat.pickup.twilightforest.ironwood_helmet":2,"stat.mineBlock.astralsorcery.blocklens":11,"stat.drop.tconstruct.slimesling":3,"stat.pickup.minecraft.bed":7,"stat.useItem.chisel.glass":589,"stat.pickup.xlfoodmod.rice_seeds":2,"stat.useItem.forge.bucketfilled":1,"stat.pickup.minecraft.potato":332,"stat.mineBlock.botania.alchemycatalyst":1,"stat.pickup.botania.altar":2,"stat.drop.botania.petal":136,"stat.craftItem.minecraft.stone_slab":24,"stat.animalsBred":5,"stat.useItem.minecraft.chest":26,"stat.drop.actuallyadditions.item_misc":19,"stat.pickup.traverse.fir_log":18,"stat.useItem.tconstruct.moms_spaghetti":204,"stat.useItem.quark.stone_marble_slab":46,"stat.mineBlock.astralsorcery.blockwell":1,"stat.craftItem.minecraft.iron_chestplate":1,"stat.pickup.minecraft.baked_potato":32,"stat.drop.minecraft.potato":4,"stat.pickup.minecraft.ender_pearl":6,"stat.pickup.twilightforest.giant_log":26,"stat.useItem.minecraft.netherrack":312,"stat.pickup.botania.managlass":643,"stat.mineBlock.minecraft.stonebrick":17,"stat.killEntity.twilightforest.winter_wolf":1,"stat.killEntity.twilightforest.bighorn_sheep":1,"stat.mineBlock.minecraft.glowstone":22,"stat.craftItem.twilightforest.yeti_helmet":1,"stat.useItem.botania.livingrock":17,"stat.craftItem.minecraft.shears":1,"stat.pickup.botania.floatingspecialflower":1,"stat.craftItem.botania.spreader":1,"stat.mineBlock.actuallyadditions.block_fermenting_barrel":1,"stat.pickup.minecraft.torch":181,"stat.mineBlock.actuallyadditions.block_grinder":1,"stat.drop.minecraft.stone_axe":1,"stat.drop.minecraft.arrow":4,"stat.pickup.ftbquests.book":4,"stat.pickup.quark.stone_marble_slab":36,"stat.killEntity.twilightforest.harbinger_cube":1,"stat.mineBlock.storagedrawers.basicdrawers":12,"stat.mineBlock.twilightforest.twilight_plant":1,"stat.killEntity.trumpetskeleton.TrumpetSkeleton":5,"stat.pickup.minecraft.lapis_block":24,"stat.pickup.astralsorcery.itemconstellationpaper":10,"stat.useItem.minecraft.mutton":7,"stat.pickup.minecraft.fishing_rod":1,"stat.useItem.minecraft.planks":26,"stat.killEntity.instrumentalmobs:FrenchHornCreeper":4,"stat.pickup.enderstorage.ender_storage":7,"stat.pickup.minecraft.porkchop":13,"stat.pickup.minecraft.glass":731,"stat.pickup.tconstruct.slimesling":4,"stat.useItem.minecraft.water_bucket":63,"stat.pickup.minecraft.sand":548,"stat.pickup.astralsorcery.blockinfusedwood":3,"stat.craftItem.actuallyadditions.item_sword_crystal_green":1,"stat.pickup.twilightforest.lamp_of_cinders":1,"stat.pickup.chisel.cobblestone2":5,"stat.drop.actuallyadditions.block_black_lotus":4,"stat.pickup.elevatorid.elevator_white":2,"stat.pickup.quark.marble":3998,"stat.pickup.quark.rune":1,"stat.useItem.chisel.netherrack":261,"stat.drop.chisel.marblepillar":2,"stat.craftItem.minecraft.blaze_powder":134,"stat.mineBlock.tconstruct.slime_grass_tall":1,"stat.killEntity.twilightforest.skeleton_druid":6,"stat.useItem.twilightforest.knightmetal_sword":27,"stat.drop.botania.flowerbag":3,"stat.pickup.actuallyadditions.item_worm":7,"stat.killEntity.twilightforest.hydra":1,"stat.pickup.astralsorcery.blockworldilluminator":4,"stat.craftItem.thermalfoundation.armor.boots_platinum":1,"stat.pickup.actuallyadditions.item_solidified_experience":232,"stat.pickup.actuallyadditions.item_sword_crystal_green":3,"stat.pickup.minecraft.furnace":7,"stat.pickup.botania.auraring":1,"stat.pickup.xlfoodmod.vanilla_flower":1,"stat.pickup.minecraft.iron_chestplate":6,"stat.pickup.minecraft.skull":1,"stat.craftItem.botania.craftinghalo":1,"stat.pickup.twilightforest.arctic_fur":34,"stat.pickup.twilightforest.raw_meef":2,"stat.pickup.botania.tinypotato":2,"stat.mineBlock.actuallyadditions.block_giant_chest":8,"stat.mineBlock.minecraft.oak_stairs":1,"stat.pickup.xlfoodmod.pepper_seeds":2,"stat.pickup.twilightforest.borer_essence":2,"stat.playOneMinute":2086836,"stat.drop.minecraft.string":3,"stat.pickup.chisel.netherbrick":61,"stat.pickup.minecraft.iron_bars":16,"stat.craftItem.minecraft.carpet":3,"stat.mineBlock.minecraft.netherrack":983,"stat.killEntity.twilightforest.death_tome":3,"stat.drop.minecraft.flint":3,"stat.pickup.twilightforest.etched_nagastone":6,"stat.fallOneCm":529793,"stat.craftItem.minecraft.chest":33,"stat.useItem.minecraft.nether_brick_fence":1,"stat.pickup.minecraft.red_mushroom":6,"stat.mineBlock.botania.livingrock":24,"stat.useItem.minecraft.iron_hoe":86,"stat.drop.traverse.fir_door":2,"stat.craftItem.astralsorcery.blockblackmarble":360,"stat.mineBlock.twilightforest.block_storage":2,"stat.pickup.minecraft.feather":12,"stat.drop.minecraft.iron_leggings":1,"stat.pickup.botania.twigwand":3,"stat.pickup.twilightforest.etched_nagastone_weathered":1,"stat.useItem.minecraft.stone_pickaxe":177,"stat.useItem.minecraft.stone_sword":25,"stat.craftItem.minecraft.iron_leggings":1,"stat.mineBlock.twilightforest.giant_log":4,"stat.pickup.botania.specialflower":58,"stat.pickup.twilightforest.trophy":22,"stat.drop.minecraft.stick":7,"stat.craftItem.draconicevolution.dislocator":3,"stat.pickup.botania.terraplate":8,"stat.killEntity.LavaSlime":8,"stat.killEntity.instrumentalmobs:MaracaSpider":8,"stat.pickup.twilightforest.ironwood_ingot":8,"stat.pickup.minecraft.log":57,"stat.pickup.twilightforest.alpha_fur":19,"stat.useItem.botania.specialflower":17,"stat.mineBlock.astralsorcery.blockcollectorcrystal":4,"stat.useItem.astralsorcery.blocklens":1,"stat.drop.botania.manatablet":7,"stat.mineBlock.chisel.glass":602,"stat.pickup.astralsorcery.blockmarbleslab":76,"stat.mineBlock.tconstruct.slime_vine_blue":1,"stat.pickup.botania.turntable":1,"stat.pickup.twilightforest.yeti_boots":1,"stat.pickup.tconstruct.slime_boots":7,"stat.drop.botania.livingrock":1,"stat.sneakTime":67201,"stat.entityKilledBy.Blaze":1,"stat.drop.thermalfoundation.tool.shield_iron":1,"stat.useItem.tconstruct.slime_congealed":1,"stat.pickup.minecraft.chest":32,"stat.useItem.minecraft.web":3,"stat.craftItem.minecraft.enchanting_table":1,"stat.drop.ftbquests.book":3,"stat.useItem.minecraft.lapis_block":11,"stat.drop.botania.runealtar":1,"stat.craftItem.botania.petal":59,"stat.mineBlock.actuallyadditions.block_misc":5,"stat.swimOneCm":87837,"stat.mineBlock.botania.floatingspecialflower":1,"stat.craftItem.botania.terraplate":1,"stat.useItem.minecraft.dirt":209,"stat.pickup.twilightforest.magic_map":2,"stat.drop.minecraft.ender_pearl":2,"stat.pickup.traverse.fir_door":6,"stat.mineBlock.chisel.limestone2":73,"stat.pickup.minecraft.glass_bottle":5,"stat.useItem.chisel.limestone2":6,"stat.drop.minecraft.wheat_seeds":34,"stat.craftItem.botania.waterrod":1,"stat.mineBlock.astralsorcery.blockaltar":4,"stat.useItem.minecraft.sign":1,"stat.pickup.minecraft.mutton":20,"stat.craftItem.astralsorcery.blockmarble":264,"stat.pickup.chisel.chisel_diamond":6,"stat.pickup.minecraft.stonebrick":21,"stat.pickup.twilightforest.ice_bomb":24,"stat.mineBlock.minecraft.nether_brick":22,"stat.useItem.twilightforest.cooked_meef":20,"stat.pickup.twilightforest.cooked_meef":10,"stat.drop.astralsorcery.itemwand":3,"stat.useItem.astralsorcery.blockmarble":1757,"stat.pickup.xlfoodmod.corn_seeds":2,"stat.craftItem.minecraft.stone_slab2":0,"stat.craftItem.quark.pickarang":1,"stat.pickup.actuallyadditions.item_misc":109,"stat.craftItem.draconicevolution.particle_generator":2,"stat.drop.minecraft.potion":2,"stat.useItem.minecraft.stone_slab":12,"stat.killEntity.twilightforest.yeti_alpha":2,"stat.craftItem.draconicevolution.wyvern_energy_core":4,"stat.craftItem.minecraft.stone":144,"stat.mineBlock.minecraft.crafting_table":11,"stat.useItem.minecraft.diamond_pickaxe":3011,"stat.useItem.minecraft.carrot":40,"stat.mineBlock.quark.world_stone_bricks":35,"stat.killEntity.twilightforest.hostile_wolf":4,"stat.pickup.thermalfoundation.armor.helmet_lead":1,"stat.pickup.minecraft.slime_ball":14,"stat.craftItem.minecraft.diamond_pickaxe":2,"stat.pickup.twilightforest.nagastone_pillar_mossy":3,"stat.craftItem.draconicevolution.dislocator_receptacle":2,"stat.pickup.minecraft.gravel":45,"stat.useItem.minecraft.glass_bottle":4,"stat.drop.actuallyadditions.item_coffee_beans":1,"stat.pickup.twilightforest.fiery_helmet":1,"stat.pickup.astralsorcery.itemrockcrystalsimple":32,"stat.pickup.minecraft.diamond_sword":5,"stat.mineBlock.refinedstorage.wireless_transmitter":1,"stat.pickup.minecraft.iron_helmet":1,"stat.craftItem.minecraft.bread":14,"stat.entityKilledBy.CaveSpider":1,"stat.pickup.minecraft.spider_eye":23,"stat.pickup.minecraft.experience_bottle":50,"stat.pickup.minecraft.iron_ore":38,"stat.pickup.tconstruct.slime_congealed":30,"stat.mineBlock.minecraft.iron_bars":8,"stat.pickup.quark.custom_chest":2,"stat.mineBlock.twilightforest.underbrick":1,"stat.pickup.minecraft.leather":17,"stat.mineBlock.instrumentalmobs.drum_block":2,"stat.useItem.astralsorcery.blockcustomore":5,"stat.craftItem.botania.spark":2,"stat.killEntity.twilightforest.minotaur":9,"stat.pickup.minecraft.reeds":19,"stat.pickup.minecraft.prismarine_crystals":3,"stat.mineBlock.tconstruct.stone_torch":1,"stat.pickup.tconstruct.materials":12,"stat.craftItem.minecraft.glass":721,"stat.sleepInBed":20,"stat.pickup.twilightforest.twilight_log":6,"stat.craftItem.minecraft.baked_potato":245,"stat.killEntity.Cow":16,"stat.killEntity.Pig":7,"stat.walkOneCm":4282189,"stat.drop.astralsorcery.itemcrystalpickaxe":3,"stat.playerKills":6,"stat.pickup.twilightforest.nagastone_pillar":1,"stat.pickup.twilightforest.phantom_chestplate":1,"stat.craftItem.quark.custom_chest":2,"stat.pickup.minecraft.clay_ball":44,"stat.craftItem.elevatorid.elevator_white":3,"stat.craftItem.botania.flowerbag":1,"stat.drop.thermalfoundation.tool.hammer_diamond":3,"stat.pickup.minecraft.stone":52,"stat.mineBlock.thermalfoundation.ore_fluid":1,"stat.pickup.minecraft.gold_ingot":1,"stat.killEntity.Skeleton":44,"stat.drop.thermalfoundation.tool.pickaxe_nickel":1,"stat.mineBlock.minecraft.redstone_torch":2,"stat.killEntity.Spider":19,"stat.pickup.minecraft.bread":14,"stat.pickup.astralsorcery.itemcraftingcomponent":27,"stat.pickup.minecraft.quartz":70,"stat.pickup.minecraft.water_bucket":1,"stat.pickup.botania.pool":4,"stat.useItem.chisel.cobblestone2":162,"stat.mineBlock.minecraft.redstone_ore":6,"stat.killEntity.twilightforest.tower_broodling":3,"stat.craftItem.draconicevolution.fusion_crafting_core":2,"stat.craftItem.minecraft.coal_block":4,"stat.craftItem.thermalfoundation.armor.plate_platinum":2,"stat.mineBlock.minecraft.stone":2149,"stat.pickup.twilightforest.meef_stroganoff":3}